wisdom_tree/__init__.py
wisdom_tree/audio.py
wisdom_tree/config.py
wisdom_tree/edit_quotes.py
wisdom_tree/main.py
wisdom_tree/qts.txt
wisdom_tree/qts_old.txt
wisdom_tree/timer.py
wisdom_tree/tree.py
wisdom_tree/ui.py
wisdom_tree/utils.py
wisdom_tree/res/alarm.wav
wisdom_tree/res/forest.ogg
wisdom_tree/res/forest2.ogg
wisdom_tree/res/growth.waw
wisdom_tree/res/logo_512x512.png
wisdom_tree/res/p1.txt
wisdom_tree/res/p2.txt
wisdom_tree/res/p3.txt
wisdom_tree/res/p4.txt
wisdom_tree/res/p5.txt
wisdom_tree/res/p6.txt
wisdom_tree/res/p7.txt
wisdom_tree/res/p8.txt
wisdom_tree/res/p9.txt
wisdom_tree/res/rain.ogg
wisdom_tree/res/rain1.txt
wisdom_tree/res/seed.txt
wisdom_tree/res/timerstart.wav
wisdom_tree/res/treedata
wisdom_tree-0.2.0.dist-info/METADATA
wisdom_tree-0.2.0.dist-info/WHEEL
wisdom_tree-0.2.0.dist-info/entry_points.txt
wisdom_tree-0.2.0.dist-info/licenses/LICENSE
wisdom_tree-0.2.0.dist-info/RECORD
