Metadata-Version: 2.4
Name: wisdom-tree
Version: 0.2.0
Summary: A terminal productivity application which lets you set pomodoro timers, show random quotes, and play music while a tree grows.
Author: HACKER097
License-File: LICENSE
Keywords: focus,pomodoro,productivity,terminal
Requires-Python: >=3.13
Requires-Dist: python-vlc>=3.0.21203
Requires-Dist: pytubefix>=9.2.0
Requires-Dist: requests>=2.32.4
